dlab/__init__.py
dlab/continuous_traces.py
dlab/dlabbehavior.py
dlab/dlabelectrical.py
dlab/eyetrackingTools.py
dlab/generalephys.py
dlab/icsd.py
dlab/load_phy_template.py
dlab/meshwarptools.py
dlab/nwbtools.py
dlab/ortho_render.py
dlab/psth_and_raster.py
dlab/reliability_and_precision.py
dlab/rf_analysis.py
dlab/sglx_analysis.py
dlab/sorting_quality.py
dlab/utils.py
denmanlab-0.4.4.dist-info/METADATA
denmanlab-0.4.4.dist-info/WHEEL
denmanlab-0.4.4.dist-info/top_level.txt
denmanlab-0.4.4.dist-info/RECORD
