Metadata-Version: 2.1
Name: denmanlab
Version: 0.4.4
Summary: denmanlab code, mostly for neurophysiology
Home-page: https://denmanlab.github.io
Author: denman lab
Author-email: daniel.denman@cuanschutz.edu
Requires-Dist: scipy
Requires-Dist: matplotlib
Requires-Dist: numpy
Requires-Dist: pandas
Requires-Dist: scikit-learn
